bw2analyzer/__init__.py
bw2analyzer/comparisons.py
bw2analyzer/contribution.py
bw2analyzer/econ.py
bw2analyzer/health_check.py
bw2analyzer/lci.py
bw2analyzer/matrix_grapher.py
bw2analyzer/page_rank.py
bw2analyzer/report.py
bw2analyzer/sc_graph.py
bw2analyzer/tagged.py
bw2analyzer/utils.py
bw2analyzer/version.py
bw2analyzer-0.11.8.dist-info/LICENSE.txt
bw2analyzer-0.11.8.dist-info/METADATA
bw2analyzer-0.11.8.dist-info/WHEEL
bw2analyzer-0.11.8.dist-info/top_level.txt
bw2analyzer-0.11.8.dist-info/RECORD
