Metadata-Version: 2.1
Name: bw2analyzer
Version: 0.11.8
Summary: UNKNOWN
Home-page: https://bitbucket.org/cmutel/brightway2-analyzer
Author: Chris Mutel
Author-email: cmutel@gmail.com
License: Copyright (c) 2016, Chris Mutel and ETH Zurich.
Platform: UNKNOWN
Classifier: Development Status :: 5 - Production/Stable
Classifier: Intended Audience :: End Users/Desktop
Classifier: Intended Audience :: Developers
Classifier: Intended Audience :: Science/Research
Classifier: License :: OSI Approved :: BSD License
Classifier: Operating System :: MacOS :: MacOS X
Classifier: Operating System :: Microsoft :: Windows
Classifier: Operating System :: POSIX
Classifier: Programming Language :: Python
Classifier: Programming Language :: Python :: 2.7
Classifier: Programming Language :: Python :: 3
Classifier: Programming Language :: Python :: 3.4
Classifier: Topic :: Scientific/Engineering :: Information Analysis
Classifier: Topic :: Scientific/Engineering :: Mathematics
Classifier: Topic :: Scientific/Engineering :: Visualization
License-File: LICENSE.txt
Requires-Dist: bw2calc >=2.0.dev14
Requires-Dist: bw2data >=4.0.dev24
Requires-Dist: matplotlib
Requires-Dist: numpy
Requires-Dist: pandas
Requires-Dist: requests
Requires-Dist: scipy
Requires-Dist: stats-arrays >=0.6.5
Requires-Dist: tabulate
Requires-Dist: tqdm
